drivefiller/__init__.py
drivefiller-3.0.1.dist-info/LICENSE
drivefiller-3.0.1.dist-info/METADATA
drivefiller-3.0.1.dist-info/WHEEL
drivefiller-3.0.1.dist-info/top_level.txt
drivefiller-3.0.1.dist-info/RECORD
