Metadata-Version: 2.1
Name: drivefiller
Version: 3.0.1
Summary: A Python 3 library that makes very large files very quickly. Can also return file size.
Home-page: https://github.com/ConorMatthews/drivefiller
Author: Conor Matthews
Author-email: conor.matthews15@gmail.com
License: UNKNOWN
Platform: UNKNOWN
Classifier: Programming Language :: Python :: 3
Classifier: License :: OSI Approved :: MIT License
Classifier: Operating System :: OS Independent
